words2number/__init__.py
words2number/words2num.py
words2number-1.0.1.dist-info/LICENSE.txt
words2number-1.0.1.dist-info/METADATA
words2number-1.0.1.dist-info/WHEEL
words2number-1.0.1.dist-info/top_level.txt
words2number-1.0.1.dist-info/RECORD
