Metadata-Version: 2.1
Name: words2number
Version: 1.0.1
Summary: Convert sentences containing numbers written in words into numeric values.
Home-page: https://github.com/benjamin-bonneton/words2number
Author: Benjamin Bonneton
Author-email: contact@benjamin-bonneton.com
Classifier: Programming Language :: Python :: 3
Classifier: License :: OSI Approved :: GNU General Public License v3 (GPLv3)
Classifier: Operating System :: OS Independent
Requires-Python: >=3.6
License-File: LICENSE.txt
